wry_py/__init__.py
wry_py/app.py
wry_py/py.typed
wry_py/wry_py.cpython-314-darwin.so
wry_py/wry_py.pyi
wry_py-0.2.3.dist-info/METADATA
wry_py-0.2.3.dist-info/WHEEL
wry_py-0.2.3.dist-info/licenses/LICENSE
wry_py-0.2.3.dist-info/RECORD
