Metadata-Version: 2.4
Name: wry_py
Version: 0.2.3
Classifier: Programming Language :: Rust
Classifier: Programming Language :: Python :: Implementation :: CPython
Classifier: Programming Language :: Python :: Implementation :: PyPy
License-File: LICENSE
Summary: Python bindings for Wry
Author-email: Jacob Walton <jacob-walton@konpeki.co.uk>
License: MIT
Requires-Python: >=3.8
Project-URL: Documentation, https://jacob-walton.github.io/wry_py/
Project-URL: Issues, https://github.com/Jacob-Walton/wry_py/issues
Project-URL: Repository, https://github.com/Jacob-Walton/wry_py
